{
  "version": "7",
  "dialect": "postgresql",
  "entries": [
    {
      "idx": 0,
      "version": "7",
      "when": 1770981059186,
      "tag": "0000_remarkable_deathstrike",
      "breakpoints": true
    },
    {
      "idx": 1,
      "version": "7",
      "when": 1770989796663,
      "tag": "0001_cute_sentry",
      "breakpoints": true
    },
    {
      "idx": 2,
      "version": "7",
      "when": 1771108008540,
      "tag": "0002_fearless_angel",
      "breakpoints": true
    },
    {
      "idx": 3,
      "version": "7",
      "when": 1739577600000,
      "tag": "0003_eloa_fts",
      "breakpoints": true
    },
    {
      "idx": 4,
      "version": "7",
      "when": 1739664000000,
      "tag": "0004_bookmark_improvements",
      "breakpoints": true
    },
    {
      "idx": 5,
      "version": "7",
      "when": 1739750400000,
      "tag": "0005_shared_sources",
      "breakpoints": true
    },
    {
      "idx": 6,
      "version": "7",
      "when": 1739836800000,
      "tag": "0006_article_read_status",
      "breakpoints": true
    },
    {
      "idx": 7,
      "version": "7",
      "when": 1739923200000,
      "tag": "0007_link_click_analytics",
      "breakpoints": true
    },
    {
      "idx": 8,
      "version": "7",
      "when": 1771333702653,
      "tag": "0008_old_trish_tilby",
      "breakpoints": true
    },
    {
      "idx": 9,
      "version": "7",
      "when": 1771337286357,
      "tag": "0009_acoustic_slapstick",
      "breakpoints": true
    }
  ]
}